agentfs_sdk/__init__.py
agentfs_sdk/agentfs.py
agentfs_sdk/constants.py
agentfs_sdk/errors.py
agentfs_sdk/filesystem.py
agentfs_sdk/guards.py
agentfs_sdk/kvstore.py
agentfs_sdk/toolcalls.py
agentfs_sdk-0.5.3.dist-info/METADATA
agentfs_sdk-0.5.3.dist-info/WHEEL
agentfs_sdk-0.5.3.dist-info/top_level.txt
agentfs_sdk-0.5.3.dist-info/RECORD
