Metadata-Version: 2.4
Name: agentfs-sdk
Version: 0.5.3
Summary: AgentFS Python SDK - A filesystem and key-value store for AI agents
Author: Turso
License: MIT
Project-URL: Homepage, https://github.com/tursodatabase/agentfs
Project-URL: Source, https://github.com/tursodatabase/agentfs
Project-URL: Repository, https://github.com/tursodatabase/agentfs
Project-URL: Issues, https://github.com/tursodatabase/agentfs/issues
Keywords: ai,agent,turso,sqlite,key-value,filesystem
Classifier: Development Status :: 3 - Alpha
Classifier: Intended Audience :: Developers
Classifier: License :: OSI Approved :: MIT License
Classifier: Operating System :: POSIX :: Linux
Classifier: Operating System :: Microsoft :: Windows
Classifier: Operating System :: MacOS
Classifier: Programming Language :: Python :: 3
Classifier: Programming Language :: Python :: 3.10
Classifier: Programming Language :: Python :: 3.11
Classifier: Programming Language :: Python :: 3.12
Classifier: Topic :: Software Development :: Libraries :: Python Modules
Requires-Python: >=3.10
Requires-Dist: pyturso==0.4.0rc17
